Workbook

Sheet DASHBOARD
B1: MOUNTTECH GROWTH FUND – KAVACHH (₹500 Cr)
B2: Fund Operations Dashboard | SEBI Cat-II AIF | Live Tracker
B5: FUND CORPUS | C5: CAPITAL CALLED | D5: DEPLOYED | E5: CASH & BANK | F5: MF NAV VALUE | G5: INVESTORS | H5: PIPELINE | I5: CONFIRMED
B6: ₹500 Cr | C6: =INPUT_Drawdown!D3 -> 0 | D6: =INPUT_Deployment!B3 -> 0 | E6: =INPUT_CashBank!C3 -> 41.3 | F6: =INPUT_MutualFund!E3 -> 58.788992 | G6: =COUNTA(INPUT_Investors!B5:B69) -> 65 | H6: =COUNTA(INPUT_Pipeline!B5:B104) -> 0 | I6: =COUNTIF(INPUT_Pipeline!G5:G104,"Confirmed") -> 0
B9: CASH & BANK BALANCES | F9: FUND DEPLOYMENT SUMMARY
B10: Bank / Account | C10: Type | D10: Balance (₹ Cr) | E10: As of Date | F10: Company / Instrument | G10: Sector | H10: Amount (₹ Cr) | I10: Date
B11: =IF(INPUT_CashBank!B4<>"",INPUT_CashBank!B4,"") -> Account Type | C11: =IF(INPUT_CashBank!C4<>"",INPUT_CashBank!C4,"") -> Balance (₹ Cr) | D11: =IF(INPUT_CashBank!D4<>"",INPUT_CashBank!D4,"") -> As of Date | E11: =IF(INPUT_CashBank!E4<>"",INPUT_CashBank!E4,"") -> Bank Branch | F11: =IF(INPUT_Deployment!B4<>"",INPUT_Deployment!B4,"") -> Sector | G11: =IF(INPUT_Deployment!C4<>"",INPUT_Deployment!C4,"") -> Amount Deployed (₹ Cr) | H11: =IF(INPUT_Deployment!D4<>"",INPUT_Deployment!D4,"") -> Investment Date | I11: =IF(INPUT_Deployment!E4<>"",INPUT_Deployment!E4,"") -> Instrument
B12: =IF(INPUT_CashBank!B5<>"",INPUT_CashBank!B5,"") -> Current Account | C12: =IF(INPUT_CashBank!C5<>"",INPUT_CashBank!C5,"") -> 12.5 | D12: =IF(INPUT_CashBank!D5<>"",INPUT_CashBank!D5,"") -> 29-Jun-2026 | E12: =IF(INPUT_CashBank!E5<>"",INPUT_CashBank!E5,"") -> Connaught Place, New Delhi | F12: =IF(INPUT_Deployment!B5<>"",INPUT_Deployment!B5,"") -> FinTech | G12: =IF(INPUT_Deployment!C5<>"",INPUT_Deployment!C5,"") -> 15 | H12: =IF(INPUT_Deployment!D5<>"",INPUT_Deployment!D5,"") -> 15-Mar-2026 | I12: =IF(INPUT_Deployment!E5<>"",INPUT_Deployment!E5,"") -> CCPS
B13: =IF(INPUT_CashBank!B6<>"",INPUT_CashBank!B6,"") -> Current Account | C13: =IF(INPUT_CashBank!C6<>"",INPUT_CashBank!C6,"") -> 3.8 | D13: =IF(INPUT_CashBank!D6<>"",INPUT_CashBank!D6,"") -> 29-Jun-2026 | E13: =IF(INPUT_CashBank!E6<>"",INPUT_CashBank!E6,"") -> Nehru Place, New Delhi | F13: =IF(INPUT_Deployment!B6<>"",INPUT_Deployment!B6,"") -> AgriTech | G13: =IF(INPUT_Deployment!C6<>"",INPUT_Deployment!C6,"") -> 10 | H13: =IF(INPUT_Deployment!D6<>"",INPUT_Deployment!D6,"") -> 01-May-2026 | I13: =IF(INPUT_Deployment!E6<>"",INPUT_Deployment!E6,"") -> Equity
B14: =IF(INPUT_CashBank!B7<>"",INPUT_CashBank!B7,"") -> Fixed Deposit | C14: =IF(INPUT_CashBank!C7<>"",INPUT_CashBank!C7,"") -> 25 | D14: =IF(INPUT_CashBank!D7<>"",INPUT_CashBank!D7,"") -> 15-Jun-2026 | E14: =IF(INPUT_CashBank!E7<>"",INPUT_CashBank!E7,"") -> Parliament Street, New Delhi | F14: =IF(INPUT_Deployment!B7<>"",INPUT_Deployment!B7,"") | G14: =IF(INPUT_Deployment!C7<>"",INPUT_Deployment!C7,"") | H14: =IF(INPUT_Deployment!D7<>"",INPUT_Deployment!D7,"") | I14: =IF(INPUT_Deployment!E7<>"",INPUT_Deployment!E7,"")
B15: =IF(INPUT_CashBank!B8<>"",INPUT_CashBank!B8,"") | C15: =IF(INPUT_CashBank!C8<>"",INPUT_CashBank!C8,"") | D15: =IF(INPUT_CashBank!D8<>"",INPUT_CashBank!D8,"") | E15: =IF(INPUT_CashBank!E8<>"",INPUT_CashBank!E8,"") | F15: =IF(INPUT_Deployment!B8<>"",INPUT_Deployment!B8,"") | G15: =IF(INPUT_Deployment!C8<>"",INPUT_Deployment!C8,"") | H15: =IF(INPUT_Deployment!D8<>"",INPUT_Deployment!D8,"") | I15: =IF(INPUT_Deployment!E8<>"",INPUT_Deployment!E8,"")
B16: =IF(INPUT_CashBank!B9<>"",INPUT_CashBank!B9,"") | C16: =IF(INPUT_CashBank!C9<>"",INPUT_CashBank!C9,"") | D16: =IF(INPUT_CashBank!D9<>"",INPUT_CashBank!D9,"") | E16: =IF(INPUT_CashBank!E9<>"",INPUT_CashBank!E9,"") | F16: =IF(INPUT_Deployment!B9<>"",INPUT_Deployment!B9,"") | G16: =IF(INPUT_Deployment!C9<>"",INPUT_Deployment!C9,"") | H16: =IF(INPUT_Deployment!D9<>"",INPUT_Deployment!D9,"") | I16: =IF(INPUT_Deployment!E9<>"",INPUT_Deployment!E9,"")
B17: =IF(INPUT_CashBank!B10<>"",INPUT_CashBank!B10,"") | C17: =IF(INPUT_CashBank!C10<>"",INPUT_CashBank!C10,"") | D17: =IF(INPUT_CashBank!D10<>"",INPUT_CashBank!D10,"") | E17: =IF(INPUT_CashBank!E10<>"",INPUT_CashBank!E10,"") | F17: =IF(INPUT_Deployment!B10<>"",INPUT_Deployment!B10,"") | G17: =IF(INPUT_Deployment!C10<>"",INPUT_Deployment!C10,"") | H17: =IF(INPUT_Deployment!D10<>"",INPUT_Deployment!D10,"") | I17: =IF(INPUT_Deployment!E10<>"",INPUT_Deployment!E10,"")
B18: =IF(INPUT_CashBank!B11<>"",INPUT_CashBank!B11,"") | C18: =IF(INPUT_CashBank!C11<>"",INPUT_CashBank!C11,"") | D18: =IF(INPUT_CashBank!D11<>"",INPUT_CashBank!D11,"") | E18: =IF(INPUT_CashBank!E11<>"",INPUT_CashBank!E11,"") | F18: =IF(INPUT_Deployment!B11<>"",INPUT_Deployment!B11,"") | G18: =IF(INPUT_Deployment!C11<>"",INPUT_Deployment!C11,"") | H18: =IF(INPUT_Deployment!D11<>"",INPUT_Deployment!D11,"") | I18: =IF(INPUT_Deployment!E11<>"",INPUT_Deployment!E11,"")
B19: TOTAL | D19: =SUM(D11:D18) -> 0 | F19: TOTAL DEPLOYED | H19: =SUM(H11:H18) -> 0
B21: MUTUAL FUND INVESTMENTS – NAV TRACKER | F21: INVESTOR DRAWDOWN SUMMARY
B22: Fund / Scheme | C22: Units Held | D22: Current NAV | E22: Market Value (₹ Cr) | F22: Investor Name | G22: Class | H22: Drawdown Called (₹ Cr) | I22: Date
B23: =IF(INPUT_MutualFund!B4<>"",INPUT_MutualFund!B4,"") -> AMC | C23: =IF(INPUT_MutualFund!C4<>"",INPUT_MutualFund!C4,"") -> Units Held | D23: =IF(INPUT_MutualFund!D4<>"",INPUT_MutualFund!D4,"") -> Latest NAV (₹) | E23: =IF(INPUT_MutualFund!E4<>"",INPUT_MutualFund!E4,"") -> Market Value (₹ Cr) | F23: =IF(INPUT_Drawdown!B4<>"",INPUT_Drawdown!B4,"") -> Investor Class | G23: =IF(INPUT_Drawdown!C4<>"",INPUT_Drawdown!C4,"") -> Drawdown Notice No. | H23: =IF(INPUT_Drawdown!D4<>"",INPUT_Drawdown!D4,"") -> Drawdown Amount (₹ Cr) | I23: =IF(INPUT_Drawdown!E4<>"",INPUT_Drawdown!E4,"") -> Notice Date
B24: =IF(INPUT_MutualFund!B5<>"",INPUT_MutualFund!B5,"") -> HDFC AMC | C24: =IF(INPUT_MutualFund!C5<>"",INPUT_MutualFund!C5,"") -> 125000 | D24: =IF(INPUT_MutualFund!D5<>"",INPUT_MutualFund!D5,"") -> 3847.52 | E24: =IF(INPUT_MutualFund!E5<>"",INPUT_MutualFund!E5,"") -> 48.094 | F24: =IF(INPUT_Drawdown!B5<>"",INPUT_Drawdown!B5,"") | G24: =IF(INPUT_Drawdown!C5<>"",INPUT_Drawdown!C5,"") | H24: =IF(INPUT_Drawdown!D5<>"",INPUT_Drawdown!D5,"") | I24: =IF(INPUT_Drawdown!E5<>"",INPUT_Drawdown!E5,"")
B25: =IF(INPUT_MutualFund!B6<>"",INPUT_MutualFund!B6,"") -> Nippon AMC | C25: =IF(INPUT_MutualFund!C6<>"",INPUT_MutualFund!C6,"") -> 88000 | D25: =IF(INPUT_MutualFund!D6<>"",INPUT_MutualFund!D6,"") -> 1215.34 | E25: =IF(INPUT_MutualFund!E6<>"",INPUT_MutualFund!E6,"") -> 10.694992 | F25: =IF(INPUT_Drawdown!B6<>"",INPUT_Drawdown!B6,"") | G25: =IF(INPUT_Drawdown!C6<>"",INPUT_Drawdown!C6,"") | H25: =IF(INPUT_Drawdown!D6<>"",INPUT_Drawdown!D6,"") | I25: =IF(INPUT_Drawdown!E6<>"",INPUT_Drawdown!E6,"")
B26: =IF(INPUT_MutualFund!B7<>"",INPUT_MutualFund!B7,"") | C26: =IF(INPUT_MutualFund!C7<>"",INPUT_MutualFund!C7,"") | D26: =IF(INPUT_MutualFund!D7<>"",INPUT_MutualFund!D7,"") | E26: =IF(INPUT_MutualFund!E7<>"",INPUT_MutualFund!E7,"") | F26: =IF(INPUT_Drawdown!B7<>"",INPUT_Drawdown!B7,"") | G26: =IF(INPUT_Drawdown!C7<>"",INPUT_Drawdown!C7,"") | H26: =IF(INPUT_Drawdown!D7<>"",INPUT_Drawdown!D7,"") | I26: =IF(INPUT_Drawdown!E7<>"",INPUT_Drawdown!E7,"")
B27: =IF(INPUT_MutualFund!B8<>"",INPUT_MutualFund!B8,"") | C27: =IF(INPUT_MutualFund!C8<>"",INPUT_MutualFund!C8,"") | D27: =IF(INPUT_MutualFund!D8<>"",INPUT_MutualFund!D8,"") | E27: =IF(INPUT_MutualFund!E8<>"",INPUT_MutualFund!E8,"") | F27: =IF(INPUT_Drawdown!B8<>"",INPUT_Drawdown!B8,"") | G27: =IF(INPUT_Drawdown!C8<>"",INPUT_Drawdown!C8,"") | H27: =IF(INPUT_Drawdown!D8<>"",INPUT_Drawdown!D8,"") | I27: =IF(INPUT_Drawdown!E8<>"",INPUT_Drawdown!E8,"")
B28: =IF(INPUT_MutualFund!B9<>"",INPUT_MutualFund!B9,"") | C28: =IF(INPUT_MutualFund!C9<>"",INPUT_MutualFund!C9,"") | D28: =IF(INPUT_MutualFund!D9<>"",INPUT_MutualFund!D9,"") | E28: =IF(INPUT_MutualFund!E9<>"",INPUT_MutualFund!E9,"") | F28: =IF(INPUT_Drawdown!B9<>"",INPUT_Drawdown!B9,"") | G28: =IF(INPUT_Drawdown!C9<>"",INPUT_Drawdown!C9,"") | H28: =IF(INPUT_Drawdown!D9<>"",INPUT_Drawdown!D9,"") | I28: =IF(INPUT_Drawdown!E9<>"",INPUT_Drawdown!E9,"")
B29: =IF(INPUT_MutualFund!B10<>"",INPUT_MutualFund!B10,"") | C29: =IF(INPUT_MutualFund!C10<>"",INPUT_MutualFund!C10,"") | D29: =IF(INPUT_MutualFund!D10<>"",INPUT_MutualFund!D10,"") | E29: =IF(INPUT_MutualFund!E10<>"",INPUT_MutualFund!E10,"") | F29: =IF(INPUT_Drawdown!B10<>"",INPUT_Drawdown!B10,"") | G29: =IF(INPUT_Drawdown!C10<>"",INPUT_Drawdown!C10,"") | H29: =IF(INPUT_Drawdown!D10<>"",INPUT_Drawdown!D10,"") | I29: =IF(INPUT_Drawdown!E10<>"",INPUT_Drawdown!E10,"")
B30: =IF(INPUT_MutualFund!B11<>"",INPUT_MutualFund!B11,"") | C30: =IF(INPUT_MutualFund!C11<>"",INPUT_MutualFund!C11,"") | D30: =IF(INPUT_MutualFund!D11<>"",INPUT_MutualFund!D11,"") | E30: =IF(INPUT_MutualFund!E11<>"",INPUT_MutualFund!E11,"") | F30: =IF(INPUT_Drawdown!B11<>"",INPUT_Drawdown!B11,"") | G30: =IF(INPUT_Drawdown!C11<>"",INPUT_Drawdown!C11,"") | H30: =IF(INPUT_Drawdown!D11<>"",INPUT_Drawdown!D11,"") | I30: =IF(INPUT_Drawdown!E11<>"",INPUT_Drawdown!E11,"")
B31: TOTAL MF VALUE | E31: =SUM(E23:E30) -> 58.788992 | F31: TOTAL DRAWDOWN CALLED | H31: =SUM(H23:H30) -> 0
B33: INVESTOR PIPELINE – STATUS SUMMARY
B34: Discussion | C34: KYC | D34: Confirmed | E34: Due Diligence | F34: KYC Completed | G34: CA Signing | H34: Drawdown Issued
B35: =COUNTIF(INPUT_Pipeline!G5:G104,"Discussion") -> 0 | C35: =COUNTIF(INPUT_Pipeline!G5:G104,"KYC") -> 0 | D35: =COUNTIF(INPUT_Pipeline!G5:G104,"Confirmed") -> 0 | E35: =COUNTIF(INPUT_Pipeline!G5:G104,"Due Diligence") -> 0 | F35: =COUNTIF(INPUT_Pipeline!G5:G104,"KYC Completed") -> 0 | G35: =COUNTIF(INPUT_Pipeline!G5:G104,"CA Signing") -> 0 | H35: =COUNTIF(INPUT_Pipeline!G5:G104,"Drawdown Issued") -> 0
B36: =COUNTIF(INPUT_Pipeline!G5:G104,"Fund Received") -> 0 | C36: ← Fund Received (Committed)
B38: MountTech Growth Fund – Kavachh | SEBI Reg. Cat-II AIF | Confidential & Restricted | Finance & Compliance – AVP

Sheet INPUT_CashBank
A1: INPUT – CASH & BANK BALANCES | MountTech Growth Fund – Kavachh
A2: ⚠ All inputs here update the DASHBOARD automatically. Enter values in INR Crore unless noted.
A3: TOTAL CASH & BANK BALANCE (₹ Cr) | C3: =SUM(C5:C24) -> 41.3
A4: Bank / Account Name | B4: Account Type | C4: Balance (₹ Cr) | D4: As of Date | E4: Bank Branch | F4: IFSC Code | G4: Account No. | H4: Remarks
A5: HDFC Bank – Escrow A/c | B5: Current Account | C5: 12.5 | D5: 29-Jun-2026 | E5: Connaught Place, New Delhi | F5: HDFC0001234 | G5: XXXXXXXXXXXX1234 | H5: Fund Escrow Account
A6: ICICI Bank – Ops A/c | B6: Current Account | C6: 3.8 | D6: 29-Jun-2026 | E6: Nehru Place, New Delhi | F6: ICIC0002345 | G6: XXXXXXXXXXXX2345 | H6: Operational Account
A7: SBI – FD | B7: Fixed Deposit | C7: 25 | D7: 15-Jun-2026 | E7: Parliament Street, New Delhi | F7: SBIN0003456 | G7: XXXXXXXXXXXX3456 | H7: 12-month FD @7.5% p.a.

Sheet INPUT_MutualFund
A1: INPUT – MUTUAL FUND – NAV TRACKER | MountTech Growth Fund – Kavachh
A2: ⚠ All inputs here update the DASHBOARD automatically. Enter values in INR Crore unless noted.
A3: TOTAL MF MARKET VALUE (₹ Cr) | E3: =SUM(E5:E24) -> 58.788992
A4: Scheme / Fund Name | B4: AMC | C4: Units Held | D4: Latest NAV (₹) | E4: Market Value (₹ Cr) | F4: Cost (₹ Cr) | G4: Unrealised G/L (₹ Cr) | H4: NAV Date | I4: ISIN | J4: Remarks
A5: HDFC Liquid Fund – Growth | B5: HDFC AMC | C5: 125000 | D5: 3847.52 | E5: =IF(C5<>"",C5*D5/10000000,"") -> 48.094 | F5: 45 | G5: =IF(E5<>"",E5-F5,"") -> 3.094 | H5: 28-Jun-2026 | I5: INF179K01VY7 | J5: Liquid parking
A6: Nippon India Overnight Fund | B6: Nippon AMC | C6: 88000 | D6: 1215.34 | E6: =IF(C6<>"",C6*D6/10000000,"") -> 10.694992 | F6: 10.2 | G6: =IF(E6<>"",E6-F6,"") -> 0.494992 | H6: 28-Jun-2026 | I6: INF204K01T90 | J6: Overnight fund
G7: =IF(E7<>"",E7-F7,"")
G8: =IF(E8<>"",E8-F8,"")
G9: =IF(E9<>"",E9-F9,"")
G10: =IF(E10<>"",E10-F10,"")
G11: =IF(E11<>"",E11-F11,"")
G12: =IF(E12<>"",E12-F12,"")
G13: =IF(E13<>"",E13-F13,"")
G14: =IF(E14<>"",E14-F14,"")
G15: =IF(E15<>"",E15-F15,"")
G16: =IF(E16<>"",E16-F16,"")
G17: =IF(E17<>"",E17-F17,"")
G18: =IF(E18<>"",E18-F18,"")
... G24: =IF(E24<>"",E24-F24,"")

Sheet INPUT_Deployment
A1: INPUT – FUND DEPLOYMENT TRACKER | MountTech Growth Fund – Kavachh
A2: ⚠ All inputs here update the DASHBOARD automatically. Enter values in INR Crore unless noted.
A3: TOTAL AMOUNT DEPLOYED (₹ Cr) | C3: =SUM(C5:C34) -> 25
A4: Portfolio Company | B4: Sector | C4: Amount Deployed (₹ Cr) | D4: Investment Date | E4: Instrument | F4: Stage | G4: Co-Investor | H4: IRR Target (%) | I4: Remarks
A5: [Portfolio Co. 1 – Placeholder] | B5: FinTech | C5: 15 | D5: 15-Mar-2026 | E5: CCPS | F5: Series A | G5: - | H5: 0.22 | I5: Lead investor
A6: [Portfolio Co. 2 – Placeholder] | B6: AgriTech | C6: 10 | D6: 01-May-2026 | E6: Equity | F6: Pre-Series A | G6: - | H6: 0.25 | I6: Co-led with XYZ

Sheet INPUT_Drawdown
A1: INPUT – CAPITAL CALLED – DRAWDOWN TRACKER | MountTech Growth Fund – Kavachh
A2: ⚠ All inputs here update the DASHBOARD automatically. Enter values in INR Crore unless noted.
A3: TOTAL CAPITAL CALLED (₹ Cr) | D3: =SUM(D5:D69) -> 0
A4: Investor Name | B4: Investor Class | C4: Drawdown Notice No. | D4: Drawdown Amount (₹ Cr) | E4: Notice Date | F4: Due Date | G4: Amount Received (₹ Cr) | H4: Receipt Date | I4: Balance Pending (₹ Cr) | J4: Remarks
I5: =IF(D5<>"",D5-IF(G5<>"",G5,0),"")
I6: =IF(D6<>"",D6-IF(G6<>"",G6,0),"")
I7: =IF(D7<>"",D7-IF(G7<>"",G7,0),"")
I8: =IF(D8<>"",D8-IF(G8<>"",G8,0),"")
I9: =IF(D9<>"",D9-IF(G9<>"",G9,0),"")
I10: =IF(D10<>"",D10-IF(G10<>"",G10,0),"")
I11: =IF(D11<>"",D11-IF(G11<>"",G11,0),"")
I12: =IF(D12<>"",D12-IF(G12<>"",G12,0),"")
I13: =IF(D13<>"",D13-IF(G13<>"",G13,0),"")
I14: =IF(D14<>"",D14-IF(G14<>"",G14,0),"")
I15: =IF(D15<>"",D15-IF(G15<>"",G15,0),"")
I16: =IF(D16<>"",D16-IF(G16<>"",G16,0),"")
... I69: =IF(D69<>"",D69-IF(G69<>"",G69,0),"")

Sheet INPUT_Investors
A1: INPUT – INVESTOR MASTER – 65 INVESTORS | MountTech Growth Fund – Kavachh
A2: ⚠ All inputs here update the DASHBOARD automatically. Enter values in INR Crore unless noted.
A3: TOTAL COMMITMENT | E3: =SUM(E5:E69) -> 0 | F3: =SUM(F5:F69) -> 0 | G3: =SUM(G5:G69) -> 0
A4: S.No. | B4: Investor Name | C4: Entity Type | D4: Investor Class | E4: Commitment (₹ Cr) | F4: Drawdown Called (₹ Cr) | G4: Balance Commitment (₹ Cr) | H4: CA Date | I4: KYC Status | J4: CKYC / KIN No. | K4: PAN No. | L4: Contact Person | M4: Email ID | N4: Mobile No. | O4: City / State | P4: Remarks
A5: 1 | B5: Investor 01 – [Family Office / HNI] | G5: =IF(E5<>"",E5-IF(F5<>"",F5,0),"")
A6: 2 | B6: Investor 02 – [Corporate Entity] | G6: =IF(E6<>"",E6-IF(F6<>"",F6,0),"")
A7: 3 | B7: Investor 03 – [Individual – HNI] | G7: =IF(E7<>"",E7-IF(F7<>"",F7,0),"")
A8: 4 | B8: Investor 04 – [Family Trust] | G8: =IF(E8<>"",E8-IF(F8<>"",F8,0),"")
A9: 5 | B9: DAK – [Class D Investor] | G9: =IF(E9<>"",E9-IF(F9<>"",F9,0),"")
A10: 6 | B10: Investor 06 – [Placeholder] | G10: =IF(E10<>"",E10-IF(F10<>"",F10,0),"")
A11: 7 | B11: Investor 07 – [Placeholder] | G11: =IF(E11<>"",E11-IF(F11<>"",F11,0),"")
A12: 8 | B12: Investor 08 – [Placeholder] | G12: =IF(E12<>"",E12-IF(F12<>"",F12,0),"")
A13: 9 | B13: Investor 09 – [Placeholder] | G13: =IF(E13<>"",E13-IF(F13<>"",F13,0),"")
A14: 10 | B14: Investor 10 – [Placeholder] | G14: =IF(E14<>"",E14-IF(F14<>"",F14,0),"")
A15: 11 | B15: Investor 11 – [Placeholder] | G15: =IF(E15<>"",E15-IF(F15<>"",F15,0),"")
A16: 12 | B16: Investor 12 – [Placeholder] | G16: =IF(E16<>"",E16-IF(F16<>"",F16,0),"")
... A69: 65 | B69: Investor 65 – [Placeholder] | G69: =IF(E69<>"",E69-IF(F69<>"",F69,0),"")

Sheet INPUT_Pipeline
A1: INPUT – INVESTOR PIPELINE TRACKER | MountTech Growth Fund – Kavachh
A2: ⚠ All inputs here update the DASHBOARD automatically. Enter values in INR Crore unless noted.
A3: TOTAL PIPELINE INVESTORS | F3: =SUMIF(G5:G104,"Confirmed",F5:F104) -> 0 | G3: ← Total Confirmed Commitment (₹ Cr)
A4: S.No. | B4: Investor Name / Entity | C4: Contact Person | D4: Mobile No. | E4: Email ID | F4: Commitment Size (₹ Cr) | G4: Pipeline Status | H4: First Meeting Date | I4: Last Interaction | J4: Next Action | K4: Next Action Date | L4: Assigned To | M4: Remarks
A5: 1
A6: 2
A7: 3
A8: 4
A9: 5
A10: 6
A11: 7
A12: 8
A13: 9
A14: 10
A15: 11
A16: 12
... A104: 100

Sheet SUMMARY_Analytics
A1: MGF – KAVACHH | Fund Analytics & Summary
A3: FUND UTILISATION SUMMARY
A4: Fund Corpus (₹ Cr) | B4: 500
A5: Capital Called (₹ Cr) | B5: =INPUT_Drawdown!D3 -> 0
A6: Amount Deployed (₹ Cr) | B6: =INPUT_Deployment!C3 -> 25
A7: Cash & Bank (₹ Cr) | B7: =INPUT_CashBank!C3 -> 41.3
A8: MF Market Value (₹ Cr) | B8: =INPUT_MutualFund!E3 -> 58.788992
A9: Deployment % of Corpus | B9: =B6/B4 -> 0.05
A10: Capital Called % of Corpus | B10: =B5/B4 -> 0
A11: Undeployed Capital (₹ Cr) | B11: =B5-B6 -> -25
A13: PIPELINE FUNNEL (AUTO-COUNTED) | B13: Count | C13: Commitment (₹ Cr)
A14: Discussion | B14: =COUNTIF(INPUT_Pipeline!G5:G104,"Discussion") -> 0 | C14: =SUMIF(INPUT_Pipeline!G5:G104,"Discussion",INPUT_Pipeline!F5:F104) -> 0
A15: KYC | B15: =COUNTIF(INPUT_Pipeline!G5:G104,"KYC") -> 0 | C15: =SUMIF(INPUT_Pipeline!G5:G104,"KYC",INPUT_Pipeline!F5:F104) -> 0
A16: Confirmed | B16: =COUNTIF(INPUT_Pipeline!G5:G104,"Confirmed") -> 0 | C16: =SUMIF(INPUT_Pipeline!G5:G104,"Confirmed",INPUT_Pipeline!F5:F104) -> 0
A17: Due Diligence | B17: =COUNTIF(INPUT_Pipeline!G5:G104,"Due Diligence") -> 0 | C17: =SUMIF(INPUT_Pipeline!G5:G104,"Due Diligence",INPUT_Pipeline!F5:F104) -> 0
A18: KYC Completed | B18: =COUNTIF(INPUT_Pipeline!G5:G104,"KYC Completed") -> 0 | C18: =SUMIF(INPUT_Pipeline!G5:G104,"KYC Completed",INPUT_Pipeline!F5:F104) -> 0
A19: CA Signing | B19: =COUNTIF(INPUT_Pipeline!G5:G104,"CA Signing") -> 0 | C19: =SUMIF(INPUT_Pipeline!G5:G104,"CA Signing",INPUT_Pipeline!F5:F104) -> 0
A20: Drawdown Issued | B20: =COUNTIF(INPUT_Pipeline!G5:G104,"Drawdown Issued") -> 0 | C20: =SUMIF(INPUT_Pipeline!G5:G104,"Drawdown Issued",INPUT_Pipeline!F5:F104) -> 0
A21: Fund Received | B21: =COUNTIF(INPUT_Pipeline!G5:G104,"Fund Received") -> 0 | C21: =SUMIF(INPUT_Pipeline!G5:G104,"Fund Received",INPUT_Pipeline!F5:F104) -> 0
A22: On Hold | B22: =COUNTIF(INPUT_Pipeline!G5:G104,"On Hold") -> 0 | C22: =SUMIF(INPUT_Pipeline!G5:G104,"On Hold",INPUT_Pipeline!F5:F104) -> 0
A23: Dropped | B23: =COUNTIF(INPUT_Pipeline!G5:G104,"Dropped") -> 0 | C23: =SUMIF(INPUT_Pipeline!G5:G104,"Dropped",INPUT_Pipeline!F5:F104) -> 0
